{"data":[{"country":"Japan","capital":"Tokyo (de facto)","population":"13,185,502","id":1},{"country":"South Korea","capital":"Seoul","population":"10,464,051","id":2},{"country":"Russia","capital":"Moscow","population":"10,126,424","id":3},{"country":"Iran","capital":"Tehran","population":"9,110,347","id":4},{"country":"Mexico","capital":"Mexico City","population":"8,841,916","id":5},{"country":"Indonesia","capital":"Jakarta","population":"8,489,910","id":6},{"country":"Colombia","capital":"Bogot\u00e1","population":"7,866,160","id":7},{"country":"China","capital":"Beijing","population":"7,741,274","id":8},{"country":"Egypt","capital":"Cairo","population":"7,438,376","id":9},{"country":"United Kingdom","capital":"London","population":"7,287,555","id":10},{"country":"Peru","capital":"Lima","population":"7,220,971","id":11},{"country":"Iraq","capital":"Baghdad","population":"7,216,040","id":12},{"country":"Hong Kong (China)","capital":"Hong Kong","population":"6,752,001","id":13},{"country":"Thailand","capital":"Bangkok","population":"6,542,751","id":14},{"country":"Bangladesh","capital":"Dhaka","population":"6,080,671","id":15},{"country":"Saudi Arabia","capital":"Riyadh","population":"5,318,636","id":16},{"country":"Chile","capital":"Santiago","population":"5,012,973","id":17},{"country":"Turkey","capital":"Ankara","population":"4,431,719","id":18},{"country":"Singapore","capital":"Singapore","population":"4,408,220","id":19},{"country":"Democratic Republic of the Congo","capital":"Kinshasa","population":"4,385,264","id":20},{"country":"Syria","capital":"Damascus","population":"3,500,000","id":21},{"country":"Germany","capital":"Berlin","population":"3,405,250","id":22},{"country":"Vietnam","capital":"Hanoi","population":"3,398,889","id":23},{"country":"Spain","capital":"Madrid","population":"3,232,463","id":24},{"country":"North Korea","capital":"Pyongyang","population":"3,144,005","id":25},{"country":"Afghanistan","capital":"Kabul","population":"3,140,853","id":26},{"country":"Argentina","capital":"Buenos Aires","population":"3,021,865","id":27},{"country":"Ethiopia","capital":"Addis Ababa","population":"2,737,479","id":28},{"country":"Kenya","capital":"Nairobi","population":"2,665,657","id":29},{"country":"Republic of China (Taiwan)","capital":"Taipei","population":"2,619,920","id":30},{"country":"Brazil","capital":"Bras\u00edlia","population":"2,606,885","id":31},{"country":"Jordan","capital":"Amman","population":"2,600,603","id":32},{"country":"Ukraine","capital":"Kiev","population":"2,591,277","id":33},{"country":"Italy","capital":"Rome","population":"2,503,056","id":34},{"country":"Angola","capital":"Luanda","population":"2,453,779","id":35},{"country":"South Africa","capital":"Pretoria","population":"2,345,908","id":36},{"country":"Cuba","capital":"Havana","population":"2,236,837","id":37},{"country":"Uzbekistan","capital":"Tashkent","population":"2,207,850","id":38},{"country":"France","capital":"Paris","population":"2,103,674","id":39},{"country":"Romania","capital":"Bucharest","population":"1,942,254","id":40},{"country":"Azerbaijan","capital":"Baku","population":"1,879,251","id":41},{"country":"Dominican Republic","capital":"Santo Domingo","population":"1,875,453","id":42},{"country":"Venezuela","capital":"Caracas","population":"1,838,939","id":43},{"country":"Morocco","capital":"Rabat","population":"1,789,635","id":44},{"country":"Sudan","capital":"Khartoum","population":"1,740,661","id":45},{"country":"Hungary","capital":"Budapest","population":"1,728,718","id":46},{"country":"Poland","capital":"Warsaw","population":"1,706,724","id":47},{"country":"Belarus","capital":"Minsk","population":"1,702,061","id":48},{"country":"Philippines","capital":"Manila","population":"1,660,714","id":49},{"country":"Uganda","capital":"Kampala","population":"1,659,600","id":50},{"country":"Ghana","capital":"Accra","population":"1,640,507","id":51},{"country":"Cameroon","capital":"Yaound\u00e9","population":"1,616,000","id":52},{"country":"Madagascar","capital":"Antananarivo","population":"1,613,375","id":53},{"country":"Lebanon","capital":"Beirut","population":"1,574,387","id":54},{"country":"Austria","capital":"Vienna","population":"1,552,789","id":55},{"country":"Algeria","capital":"Algiers","population":"1,518,083","id":56},{"country":"Ecuador","capital":"Quito","population":"1,504,991","id":57},{"country":"Zimbabwe","capital":"Harare","population":"1,487,028","id":58},{"country":"Yemen","capital":"Sana'a","population":"1,431,649","id":59},{"country":"Guinea","capital":"Conakry","population":"1,399,981","id":60},{"country":"Malaysia","capital":"Kuala Lumpur","population":"1,381,830","id":61},{"country":"Uruguay","capital":"Montevideo","population":"1,369,797","id":62},{"country":"Zambia","capital":"Lusaka","population":"1,331,254","id":63},{"country":"Somaliland","capital":"Hargeisa","population":"1,300,000","id":64},{"country":"Mali","capital":"Bamako","population":"1,289,626","id":65},{"country":"Haiti","capital":"Port-au-Prince","population":"1,235,227","id":66},{"country":"Czech Republic","capital":"Prague","population":"1,227,332","id":67},{"country":"Libya","capital":"Tripoli","population":"1,184,045","id":68},{"country":"Kuwait","capital":"Kuwait City","population":"1,171,880","id":69},{"country":"Serbia","capital":"Belgrade","population":"1,154,589","id":70},{"country":"Somalia","capital":"Mogadishu","population":"1,097,133","id":71},{"country":"Bulgaria","capital":"Sofia","population":"1,090,295","id":72},{"country":"Congo","capital":"Brazzaville","population":"1,088,044","id":73},{"country":"Belgium","capital":"Brussels","population":"1,080,790","id":74},{"country":"Armenia","capital":"Yerevan","population":"1,080,487","id":75},{"country":"Mozambique","capital":"Maputo","population":"1,076,689","id":76},{"country":"Sierra Leone","capital":"Freetown","population":"1,070,200","id":77},{"country":"Georgia","capital":"Tbilisi","population":"1,044,993","id":78},{"country":"Senegal","capital":"Dakar","population":"1,030,594","id":79},{"country":"Burkina Faso","capital":"Ouagadougou","population":"1,005,231","id":80},{"country":"Ireland","capital":"Dublin","population":"1,045,769","id":81},{"country":"Liberia","capital":"Monrovia","population":"1,010,970","id":82},{"country":"Guatemala","capital":"Guatemala City","population":"1,103,865","id":83},{"country":"Pakistan","capital":"Islamabad","population":"955,629","id":84},{"country":"Nicaragua","capital":"Managua","population":"926,883","id":85},{"country":"Myanmar","capital":"Naypyidaw","population":"925,000","id":86},{"country":"Mongolia","capital":"Ulan Bator","population":"907,802","id":87},{"country":"Malawi","capital":"Lilongwe","population":"902,388","id":88},{"country":"Canada","capital":"Ottawa","population":"898,150","id":89},{"country":"Bolivia","capital":"La Paz","population":"877,363","id":90},{"country":"Kyrgyzstan","capital":"Bishkek","population":"843,240","id":91},{"country":"Togo","capital":"Lom\u00e9","population":"824,738","id":92},{"country":"Panama","capital":"Panama City","population":"813,097","id":93},{"country":"Nepal","capital":"Kathmandu","population":"812,026","id":94},{"country":"Oman","capital":"Muscat","population":"797,000","id":95},{"country":"Niger","capital":"Niamey","population":"794,814","id":96},{"country":"Nigeria","capital":"Abuja","population":"778,567","id":97},{"country":"Sweden","capital":"Stockholm","population":"770,284","id":98},{"country":"Tunisia","capital":"Tunis","population":"767,629","id":99},{"country":"Turkmenistan","capital":"Ashgabat","population":"763,537","id":100},{"country":"Chad","capital":"N'Djamena","population":"751,288","id":101},{"country":"Israel","capital":"Jerusalem","population":"780,200","id":102},{"country":"Netherlands","capital":"Amsterdam","population":"740,094","id":103},{"country":"Honduras","capital":"Tegucigalpa","population":"735,982","id":104},{"country":"Central African Republic","capital":"Bangui","population":"731,548","id":105},{"country":"Greece","capital":"Athens","population":"721,477","id":106},{"country":"Mauritania","capital":"Nouakchott","population":"719,167","id":107},{"country":"Rwanda","capital":"Kigali","population":"718,414","id":108},{"country":"Latvia","capital":"Riga","population":"713,016","id":109},{"country":"Jamaica","capital":"Kingston","population":"701,063","id":110},{"country":"Kazakhstan","capital":"Astana","population":"700,000","id":111},{"country":"Croatia","capital":"Zagreb","population":"804,200","id":112},{"country":"Cambodia","capital":"Phnom Penh","population":"650,651","id":113},{"country":"United States","capital":"Washington, D.C.","population":"601,723","id":114},{"country":"Finland","capital":"Helsinki","population":"596,661","id":115},{"country":"Moldova","capital":"Chi\u015fin\u0103u","population":"794,800","id":116},{"country":"United Arab Emirates","capital":"Abu Dhabi","population":"585,097","id":117},{"country":"Tajikistan","capital":"Dushanbe","population":"582,496","id":118},{"country":"Lithuania","capital":"Vilnius","population":"556,723","id":119},{"country":"Gabon","capital":"Libreville","population":"556,425","id":120},{"country":"Eritrea","capital":"Asmara","population":"543,707","id":121},{"country":"Norway","capital":"Oslo","population":"575,475","id":122},{"country":"Portugal","capital":"Lisbon","population":"564,657","id":123},{"country":"El Salvador","capital":"San Salvador","population":"521,366","id":124},{"country":"Paraguay","capital":"Asunci\u00f3n","population":"520,722","id":125},{"country":"Macau (China)","capital":"Macau","population":"520,400","id":126},{"country":"Macedonia","capital":"Skopje","population":"506,926","id":127},{"country":"Denmark","capital":"Copenhagen","population":"506,166","id":128},{"country":"Djibouti","capital":"Djibouti (city)","population":"475,332","id":129},{"country":"C\u00f4te d'Ivoire","capital":"Yamoussoukro","population":"454,929","id":130},{"country":"Guinea-Bissau","capital":"Bissau","population":"452,640","id":131},{"country":"Slovakia","capital":"Bratislava","population":"424,207","id":132},{"country":"Puerto Rico (USA)","capital":"San Juan","population":"421,356","id":133},{"country":"Estonia","capital":"Tallinn","population":"403,547","id":134},{"country":"Burundi","capital":"Bujumbura","population":"384,461","id":135},{"country":"Bosnia and Herzegovina","capital":"Sarajevo","population":"383,604","id":136},{"country":"New Zealand","capital":"Wellington","population":"381,900","id":137},{"country":"Albania","capital":"Tirana","population":"763,634","id":138},{"country":"South Sudan","capital":"Juba","population":"372,410","id":139},{"country":"Australia","capital":"Canberra","population":"354,644","id":140},{"country":"Costa Rica","capital":"San Jos\u00e9","population":"328,195","id":141},{"country":"Qatar","capital":"Al-Doha","population":"303,429","id":142},{"country":"India","capital":"New Delhi","population":"292,300","id":143},{"country":"Papua New Guinea","capital":"Port Moresby","population":"299,396","id":144},{"country":"Tanzania","capital":"Dodoma","population":"287,200","id":145},{"country":"Laos","capital":"Vientiane","population":"287,579","id":146},{"country":"Cyprus","capital":"Nicosia (south)","population":"270,000","id":147},{"country":"Lesotho","capital":"Maseru","population":"267,652","id":148},{"country":"Slovenia","capital":"Ljubljana","population":"264,265","id":149},{"country":"Suriname","capital":"Paramaribo","population":"254,147","id":150},{"country":"Namibia","capital":"Windhoek","population":"252,721","id":151},{"country":"Bahamas","capital":"Nassau","population":"248,948","id":152},{"country":"Botswana","capital":"Gaborone","population":"225,656","id":153},{"country":"Benin","capital":"Porto-Novo","population":"223,552","id":154},{"country":"Western Sahara","capital":"El Aai\u00fan","population":"194,668","id":155},{"country":"Transnistria","capital":"Tiraspol","population":"159,163","id":156},{"country":"Mauritius","capital":"Port Louis","population":"147,251","id":157},{"country":"Montenegro","capital":"Podgorica","population":"141,854","id":158},{"country":"Bahrain","capital":"Manama","population":"140,616","id":159},{"country":"Guyana","capital":"Georgetown","population":"134,599","id":160},{"country":"Cape Verde","capital":"Praia","population":"125,464","id":161},{"country":"Switzerland","capital":"Berne (de facto)","population":"121,631","id":162},{"country":"Sri Lanka","capital":"Sri Jayawardenapura Kotte","population":"118,556","id":163},{"country":"Iceland","capital":"Reykjav\u00edk","population":"115,000","id":164},{"country":"Maldives","capital":"Mal\u00e9","population":"103,693","id":165},{"country":"Bhutan","capital":"Thimphu","population":"101,259","id":166},{"country":"Equatorial Guinea","capital":"Malabo","population":"100,677","id":167},{"country":"Barbados","capital":"Bridgetown","population":"96,578","id":168},{"country":"New Caledonia (France)","capital":"Noum\u00e9a","population":"89,207","id":169},{"country":"Northern Cyprus","capital":"Nicosia (north)","population":"84,893","id":170},{"country":"Fiji","capital":"Suva","population":"84,410","id":171},{"country":"Swaziland","capital":"Mbabane","population":"81,594","id":172},{"country":"Luxembourg","capital":"Luxembourg","population":"76,420","id":173},{"country":"Northern Mariana Islands (USA)","capital":"Saipan","population":"62,392","id":174},{"country":"Comoros","capital":"Moroni","population":"60,200","id":175},{"country":"Solomon Islands","capital":"Honiara","population":"59,288","id":176},{"country":"East Timor","capital":"Dili","population":"59,069","id":177},{"country":"Saint Lucia","capital":"Castries","population":"57,000","id":178},{"country":"S\u00e3o Tom\u00e9 and Pr\u00edncipe","capital":"Sao Tome","population":"56,166","id":179},{"country":"American Samoa (USA)","capital":"Pago Pago","population":"52,000","id":180},{"country":"Trinidad and Tobago","capital":"Port of Spain","population":"50,479","id":181},{"country":"Nagorno-Karabakh Republic","capital":"Stepanakert","population":"49,986","id":182},{"country":"Cura\u00e7ao (Netherlands)","capital":"Willemstad","population":"49,885","id":183},{"country":"Abkhazia","capital":"Sukhumi","population":"43,700","id":184},{"country":"Samoa","capital":"Apia","population":"39,813","id":185},{"country":"Vanuatu","capital":"Port Vila","population":"38,000","id":186},{"country":"Monaco","capital":"Monaco","population":"35,986","id":187},{"country":"Gambia","capital":"Banjul","population":"34,828","id":188},{"country":"Kiribati","capital":"Tarawa","population":"30,000","id":189},{"country":"Aruba (Netherlands)","capital":"Oranjestad","population":"29,998","id":190},{"country":"Seychelles","capital":"Victoria","population":"29,298","id":191},{"country":"Gibraltar (UK)","capital":"Gibraltar","population":"29,286","id":192},{"country":"Jersey (UK)","capital":"Saint Helier","population":"28,380","id":193},{"country":"Brunei","capital":"Bandar Seri Begawan","population":"28,135","id":194},{"country":"Cayman Islands (UK)","capital":"George Town","population":"26,798","id":195},{"country":"Isle of Man (UK)","capital":"Douglas","population":"26,600","id":196},{"country":"French Polynesia (France)","capital":"Papeete","population":"26,200","id":197},{"country":"West Bank (Israel\/PNA)","capital":"Ramallah (de facto)","population":"25,500","id":198},{"country":"Marshall Islands","capital":"Majuro","population":"25,400","id":199},{"country":"Andorra","capital":"Andorra la Vella","population":"22,884","id":200},{"country":"Antigua and Barbuda","capital":"St. John's","population":"22,679","id":201},{"country":"Tonga","capital":"Nuku\\\u02bbalofa","population":"22,400","id":202},{"country":"Faroe Islands (Denmark)","capital":"T\u00f3rshavn","population":"18,573","id":203},{"country":"Guernsey (UK)","capital":"St. Peter Port","population":"16,701","id":204},{"country":"Saint Vincent and the Grenadines","capital":"Kingstown","population":"16,031","id":205},{"country":"Greenland (Denmark)","capital":"Nuuk (Godth\u00e5b)","population":"15,469","id":206},{"country":"South Ossetia","capital":"Tskhinvali","population":"15,000","id":207},{"country":"Dominica","capital":"Roseau","population":"14,847","id":208},{"country":"Saint Kitts and Nevis","capital":"Basseterre","population":"13,043","id":209},{"country":"Belize","capital":"Belmopan","population":"12,300","id":210},{"country":"\u00c5land (Finland)","capital":"Mariehamn","population":"11,296","id":211},{"country":"United States Virgin Islands (US)","capital":"Charlotte Amalie","population":"10,817","id":212},{"country":"Federated States of Micronesia","capital":"Palikir","population":"9,900","id":213},{"country":"British Virgin Islands (UK)","capital":"Road Town","population":"9,400","id":214},{"country":"Grenada","capital":"St. George's","population":"7,500","id":215},{"country":"Malta","capital":"Valletta","population":"6,315","id":216},{"country":"Collectivity of Saint Martin (France)","capital":"Marigot","population":"5,700","id":217},{"country":"Saint Pierre and Miquelon (France)","capital":"Saint-Pierre","population":"5,509","id":218},{"country":"Cook Islands (NZ)","capital":"Avarua","population":"5,445","id":219},{"country":"Liechtenstein","capital":"Vaduz","population":"5,248","id":220},{"country":"San Marino","capital":"City of San Marino","population":"4,493","id":221},{"country":"Tuvalu","capital":"Funafuti","population":"4,492","id":222},{"country":"Turks and Caicos Islands (UK)","capital":"Cockburn Town","population":"3,700","id":223},{"country":"Saint Barth\u00e9lemy (France)","capital":"Gustavia","population":"3,000","id":224},{"country":"Falkland Islands (UK)","capital":"Stanley","population":"2,115","id":225},{"country":"Svalbard (Norway)","capital":"Longyearbyen","population":"2,075","id":226},{"country":"Christmas Island (Australia)","capital":"Flying Fish Cove","population":"1,493","id":227},{"country":"Sint Maarten (Netherlands)","capital":"Philipsburg","population":"1,338","id":228},{"country":"Wallis and Futuna (France)","capital":"Mata-Utu","population":"1,191","id":229},{"country":"Anguilla (UK)","capital":"The Valley","population":"1,169","id":230},{"country":"Nauru","capital":"Yaren (de facto)","population":"1,100","id":231},{"country":"Guam (USA)","capital":"Hag\u00e5t\u00f1a","population":"1,100","id":232},{"country":"Montserrat (UK)","capital":"Brades (de facto)","population":"1,000","id":233},{"country":"Bermuda (UK)","capital":"Hamilton","population":"969","id":234},{"country":"Norfolk Island (Australia)","capital":"Kingston","population":"880","id":235},{"country":"Holy See","capital":"The Vatican","population":"826","id":236},{"country":"Saint Helena, Ascension and Tristan da Cunha (UK)","capital":"Jamestown","population":"714","id":237},{"country":"Niue (NZ)","capital":"Alofi","population":"616","id":238},{"country":"Tokelau (NZ)","capital":"Nukunonu (de facto)","population":"426","id":239},{"country":"Palau","capital":"Ngerulmud","population":"391","id":240},{"country":"Cocos (Keeling) Islands (Australia)","capital":"West Island","population":"120","id":241},{"country":"Pitcairn Islands (UK)","capital":"Adamstown","population":"45","id":242},{"country":"South Georgia and the South Sandwich Islands (UK)","capital":"King Edward Point","population":"18","id":243}]}